datapackage_pipelines_spss/VERSION
datapackage_pipelines_spss/__init__.py
datapackage_pipelines_spss/processors/__init__.py
datapackage_pipelines_spss/processors/add_spss.py
datapackage_pipelines_spss-0.0.4a0.dist-info/DESCRIPTION.rst
datapackage_pipelines_spss-0.0.4a0.dist-info/METADATA
datapackage_pipelines_spss-0.0.4a0.dist-info/RECORD
datapackage_pipelines_spss-0.0.4a0.dist-info/WHEEL
datapackage_pipelines_spss-0.0.4a0.dist-info/metadata.json
datapackage_pipelines_spss-0.0.4a0.dist-info/top_level.txt
