Metadata-Version: 2.0
Name: datapackage-pipelines-spss
Version: 0.0.4a0
Summary: {{ DESCRIPTION }}
Home-page: https://github.com/frictionlessdata/datapackage_pipelines_spss
Author: Open Knowledge International
Author-email: UNKNOWN
License: MIT
Keywords: data
Platform: UNKNOWN
Classifier: Development Status :: 3 - Alpha
Classifier: Environment :: Web Environment
Classifier: Intended Audience :: Developers
Classifier: License :: OSI Approved :: MIT License
Classifier: Operating System :: OS Independent
Classifier: Programming Language :: Python :: 3.6
Classifier: Topic :: Internet :: WWW/HTTP :: Dynamic Content
Classifier: Topic :: Software Development :: Libraries :: Python Modules
Requires-Dist: tableschema-spss (>=0.2.0)
Requires-Dist: datapackage-pipelines (<2.0,>=1.2.1)
Provides-Extra: develop
Requires-Dist: pylama; extra == 'develop'
Requires-Dist: tox; extra == 'develop'
